geoi_core/__init__.py
geoi_core/errors/__init__.py
geoi_core/io/__init__.py
geoi_core/model/__init__.py
geoi_core/model/similarity.py
geoi_core/model/address/__init__.py
geoi_core/model/address/address.py
geoi_core/model/address/address_ner.py
geoi_core/model/basic/__init__.py
geoi_core/model/basic/geo_abstract.py
geoi_core/model/basic/geo_feature.py
geoi_core/model/basic/geo_raster.py
geoi_core/model/entity/__init__.py
geoi_core/model/entity/aoi.py
geoi_core/model/entity/loi.py
geoi_core/model/entity/poi.py
geoi_core/tests/__init__.py
geoi_core/util/__init__.py
geoi_core-0.1.1.dist-info/LICENSE
geoi_core-0.1.1.dist-info/METADATA
geoi_core-0.1.1.dist-info/WHEEL
geoi_core-0.1.1.dist-info/top_level.txt
geoi_core-0.1.1.dist-info/RECORD
