Metadata-Version: 2.1
Name: geoi-core
Version: 0.1.1
Summary: basic geographic models for intelligent application
Home-page: http://xingyun.jd.com/codingRoot/geo_intelligence/geoi_core/
Author: JUST
Author-email: suiyuan@jd.com
License: UNKNOWN
Platform: UNKNOWN
Classifier: Programming Language :: Python :: 3
Classifier: License :: OSI Approved :: MIT License
Classifier: Operating System :: OS Independent
Requires-Python: >=3.9
License-File: LICENSE
